README.md
setup.cfg
setup.py
portalutils/__init__.py
portalutils/base.py
portalutils/config.py
portalutils/exception.py
portalutils/utils.py
portalutils.egg-info/PKG-INFO
portalutils.egg-info/SOURCES.txt
portalutils.egg-info/dependency_links.txt
portalutils.egg-info/requires.txt
portalutils.egg-info/top_level.txt