Metadata-Version: 1.1
Name: portalutils
Version: 0.0.3
Summary: Portal access utility.
Home-page: https://github.com/Jack-Kingdom/portalutils.git
Author: Jack King
Author-email: email@qiaohong.org
License: MIT
Platform: UNKNOWN
Classifier: Intended Audience :: Developers
Classifier: License :: OSI Approved :: MIT License
Classifier: Programming Language :: Python
Classifier: Programming Language :: Python :: 3
Classifier: Programming Language :: Python :: 3.4
Classifier: Programming Language :: Python :: 3.5
Classifier: Programming Language :: Python :: 3.6
Classifier: Natural Language :: English
